odoo/addons/l10n_ir/README.rst
odoo/addons/l10n_ir/__init__.py
odoo/addons/l10n_ir/__manifest__.py
odoo/addons/l10n_ir/data/account.account.template.csv
odoo/addons/l10n_ir/data/account.group.template.csv
odoo/addons/l10n_ir/data/account_chart_template_data.xml
odoo/addons/l10n_ir/data/account_fiscal_position_data.xml
odoo/addons/l10n_ir/data/account_tax_group_data.xml
odoo/addons/l10n_ir/data/account_tax_report_data.xml
odoo/addons/l10n_ir/data/account_tax_template_data.xml
odoo/addons/l10n_ir/data/l10n_ir_chart_data.xml
odoo/addons/l10n_ir/data/l10n_ir_chart_post_data.xml
odoo/addons/l10n_ir/data/res.bank.csv
odoo/addons/l10n_ir/data/res_currency_data.xml
odoo/addons/l10n_ir/i18n/fa.po
odoo/addons/l10n_ir/i18n/l10n_ir.pot
odoo/addons/l10n_ir/static/description/icon.png
odoo_addon_l10n_ir-15.0.0.1.0.3.dist-info/METADATA
odoo_addon_l10n_ir-15.0.0.1.0.3.dist-info/WHEEL
odoo_addon_l10n_ir-15.0.0.1.0.3.dist-info/top_level.txt
odoo_addon_l10n_ir-15.0.0.1.0.3.dist-info/RECORD
