Metadata-Version: 2.1
Name: odoo-addon-l10n-ir
Version: 15.0.0.1.0.3
Summary: Iran Accounting Module ============================ iran accounting chart and localization. Also: - activates a number of regional currencies. - sets up Iran taxes.
Home-page: https://github.com/OCA/l10n-iran
Author: Fadoo, Odoo Community Association (OCA)
Author-email: support@odoo-community.org
License: AGPL-3
Platform: UNKNOWN
Classifier: Programming Language :: Python
Classifier: Framework :: Odoo
Classifier: Framework :: Odoo :: 15.0
Classifier: License :: OSI Approved :: GNU Affero General Public License v3
Requires-Python: >=3.8
Requires-Dist: odoo <15.1dev,>=15.0a
